odoo10_addon_account_skip_bank_reconciliation-10.0.1.0.0.99.dev3-py3.8-nspkg.pth
odoo/addons/account_skip_bank_reconciliation/README.rst
odoo/addons/account_skip_bank_reconciliation/__init__.py
odoo/addons/account_skip_bank_reconciliation/__manifest__.py
odoo/addons/account_skip_bank_reconciliation/i18n/account_skip_bank_reconciliation.pot
odoo/addons/account_skip_bank_reconciliation/models/__init__.py
odoo/addons/account_skip_bank_reconciliation/models/account_account.py
odoo/addons/account_skip_bank_reconciliation/models/account_bank_statement.py
odoo/addons/account_skip_bank_reconciliation/readme/CONTRIBUTORS.rst
odoo/addons/account_skip_bank_reconciliation/readme/DESCRIPTION.rst
odoo/addons/account_skip_bank_reconciliation/readme/USAGE.rst
odoo/addons/account_skip_bank_reconciliation/static/description/icon.png
odoo/addons/account_skip_bank_reconciliation/static/description/index.html
odoo/addons/account_skip_bank_reconciliation/views/account_view.xml
odoo10_addon_account_skip_bank_reconciliation-10.0.1.0.0.99.dev3.dist-info/METADATA
odoo10_addon_account_skip_bank_reconciliation-10.0.1.0.0.99.dev3.dist-info/WHEEL
odoo10_addon_account_skip_bank_reconciliation-10.0.1.0.0.99.dev3.dist-info/namespace_packages.txt
odoo10_addon_account_skip_bank_reconciliation-10.0.1.0.0.99.dev3.dist-info/top_level.txt
odoo10_addon_account_skip_bank_reconciliation-10.0.1.0.0.99.dev3.dist-info/RECORD
